{
	"orgPlanner": {
		"orgTitle": "",
		"settings": {
			"employeePropertyDescriptors": [
				{
					"name": "PHONE_PROPERTY_DESCRIPTOR",
					"title": "Phone",
					"defaultValue": "999-999-9999",
					"enabled": "true"
				},
				{
					"name": "LOCATION_PROPERTY_DESCRIPTOR",
					"title": "Location",
					"defaultValue": "San Francisco",
					"enabled": "true"
				}
			],
			"colorTheme": {
				"name": "DEEP_BLUE_THEME",
				"label": "Deep Blue",
				"_typeToAssignmentMap": "[object Map]"
			}
		},
		"orgSnapshots": [
			{
				"title": "1Cx5q9pZBmsyp",
				"orgStructure": {
					"employees": [
						{
							"id": "03b21008-05eb-4fdc-80a0-218955448468",
							"name": "First Last",
							"title": "Senior Vice President",
							"managerId": "ROOT",
							"isManager": true,
							"teamId": "NO_TEAM_ID",
							"properties": [
							]
						},
						{
							"id": "LSKfL",
							"name": "ecmf83 liThxo",
							"title": "9PlUZOCTai",
							"managerId": "03b21008-05eb-4fdc-80a0-218955448468",
							"isManager": false,
							"teamId": "NO_TEAM_ID",
							"properties": [
							]
						},
						{
							"id": "hyqtD",
							"name": "WnRSbu lNTVP9",
							"title": "ZKVT1wwr1o",
							"managerId": "03b21008-05eb-4fdc-80a0-218955448468",
							"isManager": false,
							"teamId": "NO_TEAM_ID",
							"properties": [
							]
						},
						{
							"id": "r8uIA",
							"name": "04wBDi 851JIm",
							"title": "VrIm1ZKeo6",
							"managerId": "03b21008-05eb-4fdc-80a0-218955448468",
							"isManager": false,
							"teamId": "NO_TEAM_ID",
							"properties": [
							]
						},
						{
							"id": "XuIPI",
							"name": "48XjRQ 4PlFer",
							"title": "iZu7Q2rght",
							"managerId": "03b21008-05eb-4fdc-80a0-218955448468",
							"isManager": false,
							"teamId": "NO_TEAM_ID",
							"properties": [
							]
						},
						{
							"id": "mMMj6",
							"name": "Mmchcp xeeMhq",
							"title": "ZYuKJemA0i",
							"managerId": "03b21008-05eb-4fdc-80a0-218955448468",
							"isManager": false,
							"teamId": "NO_TEAM_ID",
							"properties": [
							]
						},
						{
							"id": "rvjHS",
							"name": "g3ZZJc KKe6td",
							"title": "805IAut418",
							"managerId": "03b21008-05eb-4fdc-80a0-218955448468",
							"isManager": false,
							"teamId": "NO_TEAM_ID",
							"properties": [
							]
						},
						{
							"id": "aSzBD",
							"name": "Lo3ids 4mui58",
							"title": "re6P8wuWjE",
							"managerId": "03b21008-05eb-4fdc-80a0-218955448468",
							"isManager": false,
							"teamId": "NO_TEAM_ID",
							"properties": [
							]
						},
						{
							"id": "2QKjv",
							"name": "h1oaeb GDE4t8",
							"title": "gN1CqC4ljX",
							"managerId": "03b21008-05eb-4fdc-80a0-218955448468",
							"isManager": false,
							"teamId": "NO_TEAM_ID",
							"properties": [
							]
						},
						{
							"id": "57GNB",
							"name": "pgktvm Q8u3UH",
							"title": "U2tAVYMxnP",
							"managerId": "03b21008-05eb-4fdc-80a0-218955448468",
							"isManager": false,
							"teamId": "NO_TEAM_ID",
							"properties": [
							]
						},
						{
							"id": "YZA5E",
							"name": "eObAcE L3yOIq",
							"title": "GRiIbAVxbv",
							"managerId": "03b21008-05eb-4fdc-80a0-218955448468",
							"isManager": false,
							"teamId": "NO_TEAM_ID",
							"properties": [
							]
						},
						{
							"id": "rr3d8",
							"name": "aUc90s fH6m2R",
							"title": "VwKre1ZTsF",
							"managerId": "03b21008-05eb-4fdc-80a0-218955448468",
							"isManager": true,
							"teamId": "NO_TEAM_ID",
							"properties": [
							]
						},
						{
							"id": "x207w",
							"name": "XbCSjj Hz3qJd",
							"title": "bW9VMJtbBt",
							"managerId": "03b21008-05eb-4fdc-80a0-218955448468",
							"isManager": true,
							"teamId": "NO_TEAM_ID",
							"properties": [
							]
						},
						{
							"id": "JxK2J",
							"name": "w7cvh8 p7CXoS",
							"title": "l5V8DkNhSB",
							"managerId": "03b21008-05eb-4fdc-80a0-218955448468",
							"isManager": true,
							"teamId": "NO_TEAM_ID",
							"properties": [
							]
						},
						{
							"id": "wd76b",
							"name": "7ZPjNs OsHGHe",
							"title": "wjrhY208Zz",
							"managerId": "rr3d8",
							"isManager": false,
							"teamId": "NO_TEAM_ID",
							"properties": [
							]
						},
						{
							"id": "2zjtR",
							"name": "cIUwsD o18Ycm",
							"title": "hdvypf7WAe",
							"managerId": "rr3d8",
							"isManager": false,
							"teamId": "NO_TEAM_ID",
							"properties": [
							]
						},
						{
							"id": "vWWDR",
							"name": "4Kzppg x2ROet",
							"title": "3RxdXcHtmg",
							"managerId": "rr3d8",
							"isManager": false,
							"teamId": "NO_TEAM_ID",
							"properties": [
							]
						},
						{
							"id": "rUrYV",
							"name": "zEKOi4 e5CmxI",
							"title": "I2ivY8fujX",
							"managerId": "rr3d8",
							"isManager": false,
							"teamId": "NO_TEAM_ID",
							"properties": [
							]
						},
						{
							"id": "w5BAQ",
							"name": "yOZ3DO NdeBA1",
							"title": "54j3Q5Cmt2",
							"managerId": "rr3d8",
							"isManager": true,
							"teamId": "NO_TEAM_ID",
							"properties": [
							]
						},
						{
							"id": "aQagT",
							"name": "QsBTeh T6L5ax",
							"title": "MIn8anVWdC",
							"managerId": "x207w",
							"isManager": false,
							"teamId": "NO_TEAM_ID",
							"properties": [
							]
						},
						{
							"id": "2hBfr",
							"name": "mbLM9q gqO3by",
							"title": "lTxdbB5boB",
							"managerId": "x207w",
							"isManager": false,
							"teamId": "NO_TEAM_ID",
							"properties": [
							]
						},
						{
							"id": "jURka",
							"name": "lm3LZS WvJN0h",
							"title": "CAcx5tZaka",
							"managerId": "x207w",
							"isManager": false,
							"teamId": "NO_TEAM_ID",
							"properties": [
							]
						},
						{
							"id": "G9CVK",
							"name": "sy3ILn 6OYLu0",
							"title": "xLSoAVJilY",
							"managerId": "JxK2J",
							"isManager": false,
							"teamId": "NO_TEAM_ID",
							"properties": [
							]
						},
						{
							"id": "ncCz7",
							"name": "pXTgiQ O6JGjN",
							"title": "L6eS7ZprLG",
							"managerId": "JxK2J",
							"isManager": false,
							"teamId": "NO_TEAM_ID",
							"properties": [
							]
						},
						{
							"id": "IBQSp",
							"name": "gzJLbR n3iW2R",
							"title": "SvkAneSbrq",
							"managerId": "JxK2J",
							"isManager": false,
							"teamId": "NO_TEAM_ID",
							"properties": [
							]
						},
						{
							"id": "iH8b9",
							"name": "bf2PLd j7HcvM",
							"title": "d6KioCZ6ao",
							"managerId": "w5BAQ",
							"isManager": false,
							"teamId": "NO_TEAM_ID",
							"properties": [
							]
						},
						{
							"id": "zEnxZ",
							"name": "WZ4tUe akMeI4",
							"title": "ngK0VfAHKY",
							"managerId": "w5BAQ",
							"isManager": false,
							"teamId": "NO_TEAM_ID",
							"properties": [
							]
						},
						{
							"id": "uwyMs",
							"name": "d3bPXB IhiG75",
							"title": "ABlLN0oRtI",
							"managerId": "w5BAQ",
							"isManager": false,
							"teamId": "NO_TEAM_ID",
							"properties": [
							]
						},
						{
							"id": "nEBsT",
							"name": "hmyWtV PKLisI",
							"title": "OdyCnPTP96",
							"managerId": "w5BAQ",
							"isManager": false,
							"teamId": "NO_TEAM_ID",
							"properties": [
							]
						},
						{
							"id": "ZlCb5",
							"name": "czisTS ztnG2O",
							"title": "sNZV1KuvvQ",
							"managerId": "w5BAQ",
							"isManager": false,
							"teamId": "NO_TEAM_ID",
							"properties": [
							]
						},
						{
							"id": "kBVgp",
							"name": "YzGjpB xIKDb7",
							"title": "MR4P9ZOu01",
							"managerId": "w5BAQ",
							"isManager": false,
							"teamId": "NO_TEAM_ID",
							"properties": [
							]
						},
						{
							"id": "q9qFS",
							"name": "IhlrwZ oPsrOB",
							"title": "flt0ycsXSq",
							"managerId": "w5BAQ",
							"isManager": false,
							"teamId": "NO_TEAM_ID",
							"properties": [
							]
						},
						{
							"id": "Tkv39",
							"name": "mMoqSV Oiqn3c",
							"title": "B4TrQ5aOrK",
							"managerId": "w5BAQ",
							"isManager": false,
							"teamId": "NO_TEAM_ID",
							"properties": [
							]
						},
						{
							"id": "9XPAg",
							"name": "330lQv nF5RHY",
							"title": "De0i9wyXLy",
							"managerId": "w5BAQ",
							"isManager": false,
							"teamId": "NO_TEAM_ID",
							"properties": [
							]
						},
						{
							"id": "LOmCA",
							"name": "aVDdVd 5Dwl3Q",
							"title": "mObAirr1xH",
							"managerId": "w5BAQ",
							"isManager": false,
							"teamId": "NO_TEAM_ID",
							"properties": [
							]
						},
						{
							"id": "s7CUa",
							"name": "kR6JGY Qa6hDN",
							"title": "UzBBxUzEFN",
							"managerId": "w5BAQ",
							"isManager": true,
							"teamId": "NO_TEAM_ID",
							"properties": [
							]
						}
					],
					"teams": [
						{
							"id": "NO_TEAM_ID",
							"title": "-- No Team --",
							"managerId": "ROOT"
						}
					]
				}
			}
		],
		"planningProjects": [
			{
				"orgPlans": [
					{
						"title": "1Cx5q9pZBmsyp",
						"orgStructure": {
							"employees": [
								{
									"id": "03b21008-05eb-4fdc-80a0-218955448468",
									"name": "First Last",
									"title": "Senior Vice President",
									"managerId": "ROOT",
									"isManager": true,
									"teamId": "NO_TEAM_ID",
									"properties": [
									]
								},
								{
									"id": "LSKfL",
									"name": "ecmf83 liThxo",
									"title": "9PlUZOCTai",
									"managerId": "03b21008-05eb-4fdc-80a0-218955448468",
									"isManager": false,
									"teamId": "NO_TEAM_ID",
									"properties": [
									]
								},
								{
									"id": "hyqtD",
									"name": "WnRSbu lNTVP9",
									"title": "ZKVT1wwr1o",
									"managerId": "03b21008-05eb-4fdc-80a0-218955448468",
									"isManager": false,
									"teamId": "NO_TEAM_ID",
									"properties": [
									]
								},
								{
									"id": "r8uIA",
									"name": "04wBDi 851JIm",
									"title": "VrIm1ZKeo6",
									"managerId": "03b21008-05eb-4fdc-80a0-218955448468",
									"isManager": false,
									"teamId": "NO_TEAM_ID",
									"properties": [
									]
								},
								{
									"id": "XuIPI",
									"name": "48XjRQ 4PlFer",
									"title": "iZu7Q2rght",
									"managerId": "03b21008-05eb-4fdc-80a0-218955448468",
									"isManager": false,
									"teamId": "NO_TEAM_ID",
									"properties": [
									]
								},
								{
									"id": "mMMj6",
									"name": "Mmchcp xeeMhq",
									"title": "ZYuKJemA0i",
									"managerId": "03b21008-05eb-4fdc-80a0-218955448468",
									"isManager": false,
									"teamId": "NO_TEAM_ID",
									"properties": [
									]
								},
								{
									"id": "rvjHS",
									"name": "g3ZZJc KKe6td",
									"title": "805IAut418",
									"managerId": "03b21008-05eb-4fdc-80a0-218955448468",
									"isManager": false,
									"teamId": "NO_TEAM_ID",
									"properties": [
									]
								},
								{
									"id": "aSzBD",
									"name": "Lo3ids 4mui58",
									"title": "re6P8wuWjE",
									"managerId": "03b21008-05eb-4fdc-80a0-218955448468",
									"isManager": false,
									"teamId": "NO_TEAM_ID",
									"properties": [
									]
								},
								{
									"id": "2QKjv",
									"name": "h1oaeb GDE4t8",
									"title": "gN1CqC4ljX",
									"managerId": "03b21008-05eb-4fdc-80a0-218955448468",
									"isManager": false,
									"teamId": "NO_TEAM_ID",
									"properties": [
									]
								},
								{
									"id": "57GNB",
									"name": "pgktvm Q8u3UH",
									"title": "U2tAVYMxnP",
									"managerId": "03b21008-05eb-4fdc-80a0-218955448468",
									"isManager": false,
									"teamId": "NO_TEAM_ID",
									"properties": [
									]
								},
								{
									"id": "YZA5E",
									"name": "eObAcE L3yOIq",
									"title": "GRiIbAVxbv",
									"managerId": "03b21008-05eb-4fdc-80a0-218955448468",
									"isManager": false,
									"teamId": "NO_TEAM_ID",
									"properties": [
									]
								},
								{
									"id": "rr3d8",
									"name": "aUc90s fH6m2R",
									"title": "VwKre1ZTsF",
									"managerId": "03b21008-05eb-4fdc-80a0-218955448468",
									"isManager": true,
									"teamId": "NO_TEAM_ID",
									"properties": [
									]
								},
								{
									"id": "x207w",
									"name": "XbCSjj Hz3qJd",
									"title": "bW9VMJtbBt",
									"managerId": "03b21008-05eb-4fdc-80a0-218955448468",
									"isManager": true,
									"teamId": "NO_TEAM_ID",
									"properties": [
									]
								},
								{
									"id": "JxK2J",
									"name": "w7cvh8 p7CXoS",
									"title": "l5V8DkNhSB",
									"managerId": "03b21008-05eb-4fdc-80a0-218955448468",
									"isManager": true,
									"teamId": "NO_TEAM_ID",
									"properties": [
									]
								},
								{
									"id": "wd76b",
									"name": "7ZPjNs OsHGHe",
									"title": "wjrhY208Zz",
									"managerId": "rr3d8",
									"isManager": false,
									"teamId": "NO_TEAM_ID",
									"properties": [
									]
								},
								{
									"id": "2zjtR",
									"name": "cIUwsD o18Ycm",
									"title": "hdvypf7WAe",
									"managerId": "rr3d8",
									"isManager": false,
									"teamId": "NO_TEAM_ID",
									"properties": [
									]
								},
								{
									"id": "vWWDR",
									"name": "4Kzppg x2ROet",
									"title": "3RxdXcHtmg",
									"managerId": "rr3d8",
									"isManager": false,
									"teamId": "NO_TEAM_ID",
									"properties": [
									]
								},
								{
									"id": "rUrYV",
									"name": "zEKOi4 e5CmxI",
									"title": "I2ivY8fujX",
									"managerId": "rr3d8",
									"isManager": false,
									"teamId": "NO_TEAM_ID",
									"properties": [
									]
								},
								{
									"id": "w5BAQ",
									"name": "yOZ3DO NdeBA1",
									"title": "54j3Q5Cmt2",
									"managerId": "rr3d8",
									"isManager": true,
									"teamId": "NO_TEAM_ID",
									"properties": [
									]
								},
								{
									"id": "aQagT",
									"name": "QsBTeh T6L5ax",
									"title": "MIn8anVWdC",
									"managerId": "x207w",
									"isManager": false,
									"teamId": "NO_TEAM_ID",
									"properties": [
									]
								},
								{
									"id": "2hBfr",
									"name": "mbLM9q gqO3by",
									"title": "lTxdbB5boB",
									"managerId": "x207w",
									"isManager": false,
									"teamId": "NO_TEAM_ID",
									"properties": [
									]
								},
								{
									"id": "jURka",
									"name": "lm3LZS WvJN0h",
									"title": "CAcx5tZaka",
									"managerId": "x207w",
									"isManager": false,
									"teamId": "NO_TEAM_ID",
									"properties": [
									]
								},
								{
									"id": "G9CVK",
									"name": "sy3ILn 6OYLu0",
									"title": "xLSoAVJilY",
									"managerId": "JxK2J",
									"isManager": false,
									"teamId": "NO_TEAM_ID",
									"properties": [
									]
								},
								{
									"id": "ncCz7",
									"name": "pXTgiQ O6JGjN",
									"title": "L6eS7ZprLG",
									"managerId": "JxK2J",
									"isManager": false,
									"teamId": "NO_TEAM_ID",
									"properties": [
									]
								},
								{
									"id": "IBQSp",
									"name": "gzJLbR n3iW2R",
									"title": "SvkAneSbrq",
									"managerId": "JxK2J",
									"isManager": false,
									"teamId": "NO_TEAM_ID",
									"properties": [
									]
								},
								{
									"id": "iH8b9",
									"name": "bf2PLd j7HcvM",
									"title": "d6KioCZ6ao",
									"managerId": "w5BAQ",
									"isManager": false,
									"teamId": "NO_TEAM_ID",
									"properties": [
									]
								},
								{
									"id": "zEnxZ",
									"name": "WZ4tUe akMeI4",
									"title": "ngK0VfAHKY",
									"managerId": "w5BAQ",
									"isManager": false,
									"teamId": "NO_TEAM_ID",
									"properties": [
									]
								},
								{
									"id": "uwyMs",
									"name": "d3bPXB IhiG75",
									"title": "ABlLN0oRtI",
									"managerId": "w5BAQ",
									"isManager": false,
									"teamId": "NO_TEAM_ID",
									"properties": [
									]
								},
								{
									"id": "nEBsT",
									"name": "hmyWtV PKLisI",
									"title": "OdyCnPTP96",
									"managerId": "w5BAQ",
									"isManager": false,
									"teamId": "NO_TEAM_ID",
									"properties": [
									]
								},
								{
									"id": "ZlCb5",
									"name": "czisTS ztnG2O",
									"title": "sNZV1KuvvQ",
									"managerId": "w5BAQ",
									"isManager": false,
									"teamId": "NO_TEAM_ID",
									"properties": [
									]
								},
								{
									"id": "kBVgp",
									"name": "YzGjpB xIKDb7",
									"title": "MR4P9ZOu01",
									"managerId": "w5BAQ",
									"isManager": false,
									"teamId": "NO_TEAM_ID",
									"properties": [
									]
								},
								{
									"id": "q9qFS",
									"name": "IhlrwZ oPsrOB",
									"title": "flt0ycsXSq",
									"managerId": "w5BAQ",
									"isManager": false,
									"teamId": "NO_TEAM_ID",
									"properties": [
									]
								},
								{
									"id": "Tkv39",
									"name": "mMoqSV Oiqn3c",
									"title": "B4TrQ5aOrK",
									"managerId": "w5BAQ",
									"isManager": false,
									"teamId": "NO_TEAM_ID",
									"properties": [
									]
								},
								{
									"id": "9XPAg",
									"name": "330lQv nF5RHY",
									"title": "De0i9wyXLy",
									"managerId": "w5BAQ",
									"isManager": false,
									"teamId": "NO_TEAM_ID",
									"properties": [
									]
								},
								{
									"id": "LOmCA",
									"name": "aVDdVd 5Dwl3Q",
									"title": "mObAirr1xH",
									"managerId": "w5BAQ",
									"isManager": false,
									"teamId": "NO_TEAM_ID",
									"properties": [
									]
								},
								{
									"id": "s7CUa",
									"name": "kR6JGY Qa6hDN",
									"title": "UzBBxUzEFN",
									"managerId": "w5BAQ",
									"isManager": true,
									"teamId": "NO_TEAM_ID",
									"properties": [
									]
								}
							],
							"teams": [
								{
									"id": "NO_TEAM_ID",
									"title": "-- No Team --",
									"managerId": "ROOT"
								}
							]
						}
					}
				]
			}
		]
	}
}