{
	"title": "MNfyZh0NNniM46WDAILxpYng",
	"orgStructure": {
		"employees": [{
			"id": "eac5ae43-74a2-46cd-8712-0bbae3dd2092",
			"name": "First Last",
			"title": "Senior Vice President",
			"managerId": "ROOT",
			"teamId": "NO_TEAM_ID",
			"isManager": "true"
		},
		{
			"id": "6boBn",
			"name": "g9qir8 56YtTA",
			"title": "1jyt5icG2J",
			"managerId": "eac5ae43-74a2-46cd-8712-0bbae3dd2092",
			"teamId": "NO_TEAM_ID",
			"isManager": "false"
		},
		{
			"id": "CHL9Q",
			"name": "ARV47J 29dgiW",
			"title": "9UfVK5QM7X",
			"managerId": "eac5ae43-74a2-46cd-8712-0bbae3dd2092",
			"teamId": "NO_TEAM_ID",
			"isManager": "false"
		},
		{
			"id": "KdhVD",
			"name": "P6HJZK rTB6Ev",
			"title": "dNfznldGnL",
			"managerId": "eac5ae43-74a2-46cd-8712-0bbae3dd2092",
			"teamId": "NO_TEAM_ID",
			"isManager": "false"
		},
		{
			"id": "OJpIU",
			"name": "aHoZkB 0LtDs9",
			"title": "xWKgGHVCRr",
			"managerId": "eac5ae43-74a2-46cd-8712-0bbae3dd2092",
			"teamId": "NO_TEAM_ID",
			"isManager": "false"
		},
		{
			"id": "jmV6P",
			"name": "zSKhuU uiO4tW",
			"title": "MvO7xJ7Wz9",
			"managerId": "eac5ae43-74a2-46cd-8712-0bbae3dd2092",
			"teamId": "NO_TEAM_ID",
			"isManager": "false"
		},
		{
			"id": "DyP1q",
			"name": "TATxu9 WSxJUf",
			"title": "fN6txofudx",
			"managerId": "eac5ae43-74a2-46cd-8712-0bbae3dd2092",
			"teamId": "NO_TEAM_ID",
			"isManager": "false"
		},
		{
			"id": "2AZEa",
			"name": "FvQLjT JKRDar",
			"title": "RP3XAT7Yx1",
			"managerId": "eac5ae43-74a2-46cd-8712-0bbae3dd2092",
			"teamId": "NO_TEAM_ID",
			"isManager": "false"
		},
		{
			"id": "5NKqu",
			"name": "AAq6vR QjQ349",
			"title": "9oamEHgIRH",
			"managerId": "eac5ae43-74a2-46cd-8712-0bbae3dd2092",
			"teamId": "NO_TEAM_ID",
			"isManager": "false"
		},
		{
			"id": "4CJxs",
			"name": "eh957J cOSwAf",
			"title": "cIFYCG1oEF",
			"managerId": "eac5ae43-74a2-46cd-8712-0bbae3dd2092",
			"teamId": "NO_TEAM_ID",
			"isManager": "false"
		},
		{
			"id": "RXg4h",
			"name": "n9aFj4 5pt0rc",
			"title": "4m8kTvSon3",
			"managerId": "eac5ae43-74a2-46cd-8712-0bbae3dd2092",
			"teamId": "NO_TEAM_ID",
			"isManager": "false"
		},
		{
			"id": "I8ZoM",
			"name": "frlTgF TlZJTE",
			"title": "tj5zt6dH0t",
			"managerId": "eac5ae43-74a2-46cd-8712-0bbae3dd2092",
			"teamId": "NO_TEAM_ID",
			"isManager": "true"
		},
		{
			"id": "FU7bx",
			"name": "CtTbRz dHF0vk",
			"title": "SDpEvOpOJC",
			"managerId": "eac5ae43-74a2-46cd-8712-0bbae3dd2092",
			"teamId": "NO_TEAM_ID",
			"isManager": "true"
		},
		{
			"id": "s3eJx",
			"name": "DqN7sX iUrCXi",
			"title": "jBvi1fyTJS",
			"managerId": "eac5ae43-74a2-46cd-8712-0bbae3dd2092",
			"teamId": "NO_TEAM_ID",
			"isManager": "true"
		},
		{
			"id": "3Hpk7",
			"name": "PRIifj yYn39f",
			"title": "bfpgH7jbMr",
			"managerId": "I8ZoM",
			"teamId": "NO_TEAM_ID",
			"isManager": "false"
		},
		{
			"id": "lWiYP",
			"name": "4It53l JsuV6e",
			"title": "zJZZdwwyXN",
			"managerId": "I8ZoM",
			"teamId": "NO_TEAM_ID",
			"isManager": "false"
		},
		{
			"id": "SE9TO",
			"name": "dwlFEk StT5eZ",
			"title": "uiXeGKRIi8",
			"managerId": "I8ZoM",
			"teamId": "NO_TEAM_ID",
			"isManager": "false"
		},
		{
			"id": "gj1Kr",
			"name": "1OhsTl s1mvDB",
			"title": "vekbAJL1bj",
			"managerId": "I8ZoM",
			"teamId": "NO_TEAM_ID",
			"isManager": "false"
		},
		{
			"id": "iZIcC",
			"name": "RTCpZM xS7jzP",
			"title": "2cIrhh3UMR",
			"managerId": "I8ZoM",
			"teamId": "NO_TEAM_ID",
			"isManager": "true"
		},
		{
			"id": "isn4m",
			"name": "GgjTOk 5tc50o",
			"title": "HV3TQakbtu",
			"managerId": "I8ZoM",
			"teamId": "NO_TEAM_ID",
			"isManager": "true"
		},
		{
			"id": "drK2v",
			"name": "Bjcdnu e9mPwa",
			"title": "NIZZ9VJhZZ",
			"managerId": "I8ZoM",
			"teamId": "NO_TEAM_ID",
			"isManager": "true"
		},
		{
			"id": "Xgb0c",
			"name": "8PrVm2 uQXLSW",
			"title": "6hajKoQ4KK",
			"managerId": "FU7bx",
			"teamId": "NO_TEAM_ID",
			"isManager": "false"
		},
		{
			"id": "nFXJP",
			"name": "KlZO3k tCvztq",
			"title": "CY1BplfiYd",
			"managerId": "FU7bx",
			"teamId": "NO_TEAM_ID",
			"isManager": "false"
		},
		{
			"id": "JUfzb",
			"name": "evRTgs pzpk9u",
			"title": "e36mCuntjI",
			"managerId": "FU7bx",
			"teamId": "NO_TEAM_ID",
			"isManager": "false"
		},
		{
			"id": "ySc1p",
			"name": "vQDX62 gvgSdw",
			"title": "GY42XE1BEY",
			"managerId": "FU7bx",
			"teamId": "NO_TEAM_ID",
			"isManager": "true"
		},
		{
			"id": "CxBXx",
			"name": "bjHJDM LGvXnA",
			"title": "NHOeDfyNOH",
			"managerId": "FU7bx",
			"teamId": "NO_TEAM_ID",
			"isManager": "true"
		},
		{
			"id": "X7cuc",
			"name": "M5bOfu YhQRdV",
			"title": "41orBkelxG",
			"managerId": "FU7bx",
			"teamId": "NO_TEAM_ID",
			"isManager": "true"
		},
		{
			"id": "FlJlg",
			"name": "bIjY7r HVg0gg",
			"title": "lUxGyRtnuy",
			"managerId": "s3eJx",
			"teamId": "NO_TEAM_ID",
			"isManager": "false"
		},
		{
			"id": "zEEW1",
			"name": "zunqN1 bV7J6p",
			"title": "PIXS8TY1sq",
			"managerId": "s3eJx",
			"teamId": "NO_TEAM_ID",
			"isManager": "false"
		},
		{
			"id": "gFjl6",
			"name": "TPL8nB OXJnFa",
			"title": "OZi9yRYstR",
			"managerId": "s3eJx",
			"teamId": "NO_TEAM_ID",
			"isManager": "false"
		},
		{
			"id": "tadTw",
			"name": "wOPdSB sUsnFE",
			"title": "fYRZHR2bFN",
			"managerId": "s3eJx",
			"teamId": "NO_TEAM_ID",
			"isManager": "true"
		},
		{
			"id": "8q67r",
			"name": "vOo0kn eNCDVZ",
			"title": "fvCRsAeJqp",
			"managerId": "s3eJx",
			"teamId": "NO_TEAM_ID",
			"isManager": "true"
		},
		{
			"id": "57yDN",
			"name": "Zfjs25 WHgkyc",
			"title": "Vr3vwJ5Q6i",
			"managerId": "s3eJx",
			"teamId": "NO_TEAM_ID",
			"isManager": "true"
		},
		{
			"id": "Z6jj3",
			"name": "FHEMe9 B8tXjJ",
			"title": "aDbiurFacd",
			"managerId": "iZIcC",
			"teamId": "NO_TEAM_ID",
			"isManager": "false"
		},
		{
			"id": "cVNcp",
			"name": "yVjB2N wqYD3K",
			"title": "hTJ5tCobp0",
			"managerId": "iZIcC",
			"teamId": "NO_TEAM_ID",
			"isManager": "false"
		},
		{
			"id": "u1BKM",
			"name": "YUOzKI xlZw2J",
			"title": "n0q0tS8Ccc",
			"managerId": "iZIcC",
			"teamId": "NO_TEAM_ID",
			"isManager": "true"
		},
		{
			"id": "gHrAO",
			"name": "xS3phQ 2uE4aQ",
			"title": "5fJVgWoHZr",
			"managerId": "isn4m",
			"teamId": "NO_TEAM_ID",
			"isManager": "false"
		},
		{
			"id": "2H68a",
			"name": "8dg2vM OS99xW",
			"title": "1OVRCHqJGb",
			"managerId": "drK2v",
			"teamId": "NO_TEAM_ID",
			"isManager": "false"
		},
		{
			"id": "SuXhl",
			"name": "xxahPq 2j5oTt",
			"title": "HmuFef6PhI",
			"managerId": "ySc1p",
			"teamId": "NO_TEAM_ID",
			"isManager": "false"
		},
		{
			"id": "X2ADb",
			"name": "Kb3b6f P0IV0b",
			"title": "CKfp1HqDi7",
			"managerId": "CxBXx",
			"teamId": "NO_TEAM_ID",
			"isManager": "false"
		},
		{
			"id": "ANNGD",
			"name": "mS54AB nRcHOS",
			"title": "oyKEt5Dtsj",
			"managerId": "X7cuc",
			"teamId": "NO_TEAM_ID",
			"isManager": "false"
		},
		{
			"id": "grBlY",
			"name": "rxTHE9 tELZaU",
			"title": "zQVvjIOQmN",
			"managerId": "tadTw",
			"teamId": "NO_TEAM_ID",
			"isManager": "false"
		},
		{
			"id": "MrbLp",
			"name": "1MfHrF Tj0tGd",
			"title": "XTAaZUVdQn",
			"managerId": "8q67r",
			"teamId": "NO_TEAM_ID",
			"isManager": "false"
		},
		{
			"id": "shNqo",
			"name": "c17OM5 7RtTYs",
			"title": "H9PnI6hgmo",
			"managerId": "57yDN",
			"teamId": "NO_TEAM_ID",
			"isManager": "false"
		}],
		"teams": [{
			"id": "NO_TEAM_ID",
			"title": "-- No Team --",
			"managerId": "ROOT"
		}]
	}
}