{
	"title": "Pg5IuF7kmmSxYjQY",
	"orgStructure": {
		"employees": [{
			"id": "ad173d66-bc3b-4b18-a94d-f162f54cd0ad",
			"name": "First Last",
			"title": "Senior Vice President",
			"managerId": "ROOT",
			"teamId": "NO_TEAM_ID",
			"isManager": "true"
		},
		{
			"id": "DEcuY",
			"name": "9PAs7P o4wsLz",
			"title": "GiZOyoO1Yl",
			"managerId": "ad173d66-bc3b-4b18-a94d-f162f54cd0ad",
			"teamId": "NO_TEAM_ID",
			"isManager": "false"
		},
		{
			"id": "lRE6h",
			"name": "tTl41i XKsvFd",
			"title": "lPA0aVQ5IC",
			"managerId": "ad173d66-bc3b-4b18-a94d-f162f54cd0ad",
			"teamId": "NO_TEAM_ID",
			"isManager": "false"
		},
		{
			"id": "YMCnD",
			"name": "KUFT2q 7hnVr1",
			"title": "Clj9bs7nRz",
			"managerId": "ad173d66-bc3b-4b18-a94d-f162f54cd0ad",
			"teamId": "NO_TEAM_ID",
			"isManager": "false"
		},
		{
			"id": "S0hJr",
			"name": "1ZXjF2 JgTxal",
			"title": "68hAzHdiBs",
			"managerId": "ad173d66-bc3b-4b18-a94d-f162f54cd0ad",
			"teamId": "NO_TEAM_ID",
			"isManager": "false"
		},
		{
			"id": "8Nrfb",
			"name": "QMf6mZ FGGOqO",
			"title": "3Pt15bUFKx",
			"managerId": "ad173d66-bc3b-4b18-a94d-f162f54cd0ad",
			"teamId": "NO_TEAM_ID",
			"isManager": "false"
		},
		{
			"id": "TaC62",
			"name": "v7B2SR NzkaoA",
			"title": "4MbZiVIvDJ",
			"managerId": "ad173d66-bc3b-4b18-a94d-f162f54cd0ad",
			"teamId": "NO_TEAM_ID",
			"isManager": "false"
		},
		{
			"id": "6ChdD",
			"name": "uyFvIF R3qUej",
			"title": "LCECehg13l",
			"managerId": "ad173d66-bc3b-4b18-a94d-f162f54cd0ad",
			"teamId": "NO_TEAM_ID",
			"isManager": "false"
		},
		{
			"id": "b5bRF",
			"name": "dfcbmj 8YwVDj",
			"title": "R5TqADy6bt",
			"managerId": "ad173d66-bc3b-4b18-a94d-f162f54cd0ad",
			"teamId": "NO_TEAM_ID",
			"isManager": "false"
		},
		{
			"id": "QVZT1",
			"name": "tZO2kj LrqWOF",
			"title": "Joie1RDjKX",
			"managerId": "ad173d66-bc3b-4b18-a94d-f162f54cd0ad",
			"teamId": "NO_TEAM_ID",
			"isManager": "false"
		},
		{
			"id": "nfdle",
			"name": "QdqimT xkFf0M",
			"title": "nTWApB4DPT",
			"managerId": "ad173d66-bc3b-4b18-a94d-f162f54cd0ad",
			"teamId": "NO_TEAM_ID",
			"isManager": "false"
		},
		{
			"id": "wSPdn",
			"name": "7R6Nh6 xNNH7N",
			"title": "JqFuezqzmn",
			"managerId": "ad173d66-bc3b-4b18-a94d-f162f54cd0ad",
			"teamId": "NO_TEAM_ID",
			"isManager": "true"
		},
		{
			"id": "Bv5Mn",
			"name": "EybHTa B7eeAh",
			"title": "1jNXTuohj5",
			"managerId": "wSPdn",
			"teamId": "NO_TEAM_ID",
			"isManager": "true"
		},
		{
			"id": "feaBJ",
			"name": "pZSgap amSS2T",
			"title": "BxEKLOlraM",
			"managerId": "Bv5Mn",
			"teamId": "NO_TEAM_ID",
			"isManager": "false"
		}],
		"teams": [{
			"id": "NO_TEAM_ID",
			"title": "-- No Team --",
			"managerId": "ROOT"
		}]
	}
}