{
	"serializationDescriptor": {
		"name": "OrgDataCore",
		"objectVersion": "1"
	},
	"title": "ezSYHmGi1mzsOe",
	"orgStructure": {
		"serializationDescriptor": {
			"name": "OrgStructure",
			"objectVersion": "1"
		},
		"employeePropertyDescriptors": [{
			"serializationDescriptor": {
				"name": "OrgEntityPropertyDescriptor",
				"objectVersion": "1"
			},
			"name": "PHONE_PROPERTY_DESCRIPTOR",
			"title": "Phone",
			"defaultValue": "999-999-9999",
			"defaultVisibility": "false",
			"enabled": "true"
		},
		{
			"serializationDescriptor": {
				"name": "OrgEntityPropertyDescriptor",
				"objectVersion": "1"
			},
			"name": "LOCATION_PROPERTY_DESCRIPTOR",
			"title": "Location",
			"defaultValue": "San Francisco",
			"defaultVisibility": "true",
			"enabled": "true"
		}],
		"employees": [{
			"serializationDescriptor": {
				"name": "Manager",
				"objectVersion": "1"
			},
			"id": "5735cd89-7e68-4ad0-b313-d4e0b95a5087",
			"name": "First Last",
			"properties": [{"name":"PHONE_PROPERTY_DESCRIPTOR",
"value":"999-999-9999"}
,{"name":"LOCATION_PROPERTY_DESCRIPTOR",
"value":"Your Location"}
],
			"title": "Your Job Title",
			"managerId": "ROOT_ID",
			"teamId": "b566f7a3-19d7-4608-9e96-327bcbb1b2b0",
			"isManager": "true"
		},
		{
			"serializationDescriptor": {
				"name": "IndividualContributor",
				"objectVersion": "1"
			},
			"id": "gdiH7",
			"name": "duwJNL Q8XxXc",
			"properties": [{"name":"PHONE_PROPERTY_DESCRIPTOR",
"value":"999-999-9999"}
,{"name":"LOCATION_PROPERTY_DESCRIPTOR",
"value":"New York, NY"}
],
			"title": "irx88CKtlQ",
			"managerId": "5735cd89-7e68-4ad0-b313-d4e0b95a5087",
			"teamId": "NO_TEAM_ID",
			"isManager": "false"
		},
		{
			"serializationDescriptor": {
				"name": "IndividualContributor",
				"objectVersion": "1"
			},
			"id": "fCoeY",
			"name": "GN9xea eDA2yb",
			"properties": [{"name":"PHONE_PROPERTY_DESCRIPTOR",
"value":"999-999-9999"}
,{"name":"LOCATION_PROPERTY_DESCRIPTOR",
"value":"Austin, TX"}
],
			"title": "Itu4JgvdKy",
			"managerId": "5735cd89-7e68-4ad0-b313-d4e0b95a5087",
			"teamId": "NO_TEAM_ID",
			"isManager": "false"
		},
		{
			"serializationDescriptor": {
				"name": "IndividualContributor",
				"objectVersion": "1"
			},
			"id": "GtWsV",
			"name": "CJYmos S93LRP",
			"properties": [{"name":"PHONE_PROPERTY_DESCRIPTOR",
"value":"999-999-9999"}
,{"name":"LOCATION_PROPERTY_DESCRIPTOR",
"value":"New York, NY"}
],
			"title": "D6Z5kuSMvO",
			"managerId": "5735cd89-7e68-4ad0-b313-d4e0b95a5087",
			"teamId": "NO_TEAM_ID",
			"isManager": "false"
		},
		{
			"serializationDescriptor": {
				"name": "IndividualContributor",
				"objectVersion": "1"
			},
			"id": "nnXUN",
			"name": "niaHaK Nkd2V3",
			"properties": [{"name":"PHONE_PROPERTY_DESCRIPTOR",
"value":"999-999-9999"}
,{"name":"LOCATION_PROPERTY_DESCRIPTOR",
"value":"New York, NY"}
],
			"title": "rLWyVqzYdH",
			"managerId": "5735cd89-7e68-4ad0-b313-d4e0b95a5087",
			"teamId": "NO_TEAM_ID",
			"isManager": "false"
		},
		{
			"serializationDescriptor": {
				"name": "IndividualContributor",
				"objectVersion": "1"
			},
			"id": "ccEwd",
			"name": "9ZhavK Sw4LLr",
			"properties": [{"name":"PHONE_PROPERTY_DESCRIPTOR",
"value":"999-999-9999"}
,{"name":"LOCATION_PROPERTY_DESCRIPTOR",
"value":"New York, NY"}
],
			"title": "TNR7OZG8RD",
			"managerId": "5735cd89-7e68-4ad0-b313-d4e0b95a5087",
			"teamId": "NO_TEAM_ID",
			"isManager": "false"
		},
		{
			"serializationDescriptor": {
				"name": "IndividualContributor",
				"objectVersion": "1"
			},
			"id": "7W0pJ",
			"name": "YOOOmU F7Ebf0",
			"properties": [{"name":"PHONE_PROPERTY_DESCRIPTOR",
"value":"999-999-9999"}
,{"name":"LOCATION_PROPERTY_DESCRIPTOR",
"value":"San Francisco, CA"}
],
			"title": "tmEFB5jw2F",
			"managerId": "5735cd89-7e68-4ad0-b313-d4e0b95a5087",
			"teamId": "NO_TEAM_ID",
			"isManager": "false"
		},
		{
			"serializationDescriptor": {
				"name": "IndividualContributor",
				"objectVersion": "1"
			},
			"id": "7E2xG",
			"name": "dSxYwX MW8Q1r",
			"properties": [{"name":"PHONE_PROPERTY_DESCRIPTOR",
"value":"999-999-9999"}
,{"name":"LOCATION_PROPERTY_DESCRIPTOR",
"value":"New York, NY"}
],
			"title": "YayD3zMyAP",
			"managerId": "5735cd89-7e68-4ad0-b313-d4e0b95a5087",
			"teamId": "NO_TEAM_ID",
			"isManager": "false"
		},
		{
			"serializationDescriptor": {
				"name": "IndividualContributor",
				"objectVersion": "1"
			},
			"id": "Jwdlx",
			"name": "z18bC4 k3Yoz7",
			"properties": [{"name":"PHONE_PROPERTY_DESCRIPTOR",
"value":"999-999-9999"}
,{"name":"LOCATION_PROPERTY_DESCRIPTOR",
"value":"Austin, TX"}
],
			"title": "HBRDtmXscL",
			"managerId": "5735cd89-7e68-4ad0-b313-d4e0b95a5087",
			"teamId": "NO_TEAM_ID",
			"isManager": "false"
		},
		{
			"serializationDescriptor": {
				"name": "IndividualContributor",
				"objectVersion": "1"
			},
			"id": "OPrE7",
			"name": "9M2qMP XEivzl",
			"properties": [{"name":"PHONE_PROPERTY_DESCRIPTOR",
"value":"999-999-9999"}
,{"name":"LOCATION_PROPERTY_DESCRIPTOR",
"value":"San Francisco, CA"}
],
			"title": "iMSOE6LuwQ",
			"managerId": "5735cd89-7e68-4ad0-b313-d4e0b95a5087",
			"teamId": "NO_TEAM_ID",
			"isManager": "false"
		},
		{
			"serializationDescriptor": {
				"name": "IndividualContributor",
				"objectVersion": "1"
			},
			"id": "mXPRX",
			"name": "17qTih 7xoW1S",
			"properties": [{"name":"PHONE_PROPERTY_DESCRIPTOR",
"value":"999-999-9999"}
,{"name":"LOCATION_PROPERTY_DESCRIPTOR",
"value":"New York, NY"}
],
			"title": "byeZXOldD9",
			"managerId": "5735cd89-7e68-4ad0-b313-d4e0b95a5087",
			"teamId": "NO_TEAM_ID",
			"isManager": "false"
		},
		{
			"serializationDescriptor": {
				"name": "Manager",
				"objectVersion": "1"
			},
			"id": "YR4MD",
			"name": "p6GcRZ FKPG9z",
			"properties": [{"name":"PHONE_PROPERTY_DESCRIPTOR",
"value":"999-999-9999"}
,{"name":"LOCATION_PROPERTY_DESCRIPTOR",
"value":"San Francisco, CA"}
],
			"title": "WpA0SP6jn4",
			"managerId": "5735cd89-7e68-4ad0-b313-d4e0b95a5087",
			"teamId": "NO_TEAM_ID",
			"isManager": "true"
		},
		{
			"serializationDescriptor": {
				"name": "Manager",
				"objectVersion": "1"
			},
			"id": "6DXHo",
			"name": "WAl636 QavqXn",
			"properties": [{"name":"PHONE_PROPERTY_DESCRIPTOR",
"value":"999-999-9999"}
,{"name":"LOCATION_PROPERTY_DESCRIPTOR",
"value":"Austin, TX"}
],
			"title": "x50XCIMm3b",
			"managerId": "5735cd89-7e68-4ad0-b313-d4e0b95a5087",
			"teamId": "NO_TEAM_ID",
			"isManager": "true"
		},
		{
			"serializationDescriptor": {
				"name": "Manager",
				"objectVersion": "1"
			},
			"id": "127AO",
			"name": "24soBk Zvbn5g",
			"properties": [{"name":"PHONE_PROPERTY_DESCRIPTOR",
"value":"999-999-9999"}
,{"name":"LOCATION_PROPERTY_DESCRIPTOR",
"value":"New York, NY"}
],
			"title": "uf7aJ67KWv",
			"managerId": "5735cd89-7e68-4ad0-b313-d4e0b95a5087",
			"teamId": "NO_TEAM_ID",
			"isManager": "true"
		},
		{
			"serializationDescriptor": {
				"name": "IndividualContributor",
				"objectVersion": "1"
			},
			"id": "hEL8Z",
			"name": "WvCiRo S9fHGJ",
			"properties": [{"name":"PHONE_PROPERTY_DESCRIPTOR",
"value":"999-999-9999"}
,{"name":"LOCATION_PROPERTY_DESCRIPTOR",
"value":"San Francisco, CA"}
],
			"title": "vAVxE3lzAg",
			"managerId": "YR4MD",
			"teamId": "NO_TEAM_ID",
			"isManager": "false"
		},
		{
			"serializationDescriptor": {
				"name": "IndividualContributor",
				"objectVersion": "1"
			},
			"id": "fDEkF",
			"name": "uC8tt4 4wCYft",
			"properties": [{"name":"PHONE_PROPERTY_DESCRIPTOR",
"value":"999-999-9999"}
,{"name":"LOCATION_PROPERTY_DESCRIPTOR",
"value":"New York, NY"}
],
			"title": "uFAdWymfhe",
			"managerId": "YR4MD",
			"teamId": "NO_TEAM_ID",
			"isManager": "false"
		},
		{
			"serializationDescriptor": {
				"name": "IndividualContributor",
				"objectVersion": "1"
			},
			"id": "2X0Wt",
			"name": "pvYon3 OQDHfW",
			"properties": [{"name":"PHONE_PROPERTY_DESCRIPTOR",
"value":"999-999-9999"}
,{"name":"LOCATION_PROPERTY_DESCRIPTOR",
"value":"San Francisco, CA"}
],
			"title": "5KU83vBiDX",
			"managerId": "YR4MD",
			"teamId": "NO_TEAM_ID",
			"isManager": "false"
		},
		{
			"serializationDescriptor": {
				"name": "IndividualContributor",
				"objectVersion": "1"
			},
			"id": "MAsrN",
			"name": "0DHAb3 mepDVg",
			"properties": [{"name":"PHONE_PROPERTY_DESCRIPTOR",
"value":"999-999-9999"}
,{"name":"LOCATION_PROPERTY_DESCRIPTOR",
"value":"San Francisco, CA"}
],
			"title": "MiyyUkRqar",
			"managerId": "YR4MD",
			"teamId": "NO_TEAM_ID",
			"isManager": "false"
		},
		{
			"serializationDescriptor": {
				"name": "Manager",
				"objectVersion": "1"
			},
			"id": "J6aJB",
			"name": "bO8i7C xmjv5r",
			"properties": [{"name":"PHONE_PROPERTY_DESCRIPTOR",
"value":"999-999-9999"}
,{"name":"LOCATION_PROPERTY_DESCRIPTOR",
"value":"New York, NY"}
],
			"title": "6QPEByJ9yV",
			"managerId": "YR4MD",
			"teamId": "NO_TEAM_ID",
			"isManager": "true"
		},
		{
			"serializationDescriptor": {
				"name": "Manager",
				"objectVersion": "1"
			},
			"id": "IXhya",
			"name": "CM4QJH lAJ8iZ",
			"properties": [{"name":"PHONE_PROPERTY_DESCRIPTOR",
"value":"999-999-9999"}
,{"name":"LOCATION_PROPERTY_DESCRIPTOR",
"value":"New York, NY"}
],
			"title": "FexcwB4F63",
			"managerId": "YR4MD",
			"teamId": "NO_TEAM_ID",
			"isManager": "true"
		},
		{
			"serializationDescriptor": {
				"name": "Manager",
				"objectVersion": "1"
			},
			"id": "QZkJj",
			"name": "nBk6Z5 q5b5Gv",
			"properties": [{"name":"PHONE_PROPERTY_DESCRIPTOR",
"value":"999-999-9999"}
,{"name":"LOCATION_PROPERTY_DESCRIPTOR",
"value":"Austin, TX"}
],
			"title": "z4eyJny3Ka",
			"managerId": "YR4MD",
			"teamId": "NO_TEAM_ID",
			"isManager": "true"
		},
		{
			"serializationDescriptor": {
				"name": "IndividualContributor",
				"objectVersion": "1"
			},
			"id": "CQtGf",
			"name": "wDlxof 3mg7Vo",
			"properties": [{"name":"PHONE_PROPERTY_DESCRIPTOR",
"value":"999-999-9999"}
,{"name":"LOCATION_PROPERTY_DESCRIPTOR",
"value":"Austin, TX"}
],
			"title": "1hDJbwKkRZ",
			"managerId": "6DXHo",
			"teamId": "NO_TEAM_ID",
			"isManager": "false"
		},
		{
			"serializationDescriptor": {
				"name": "IndividualContributor",
				"objectVersion": "1"
			},
			"id": "jp49x",
			"name": "UKEH5H nNFYHP",
			"properties": [{"name":"PHONE_PROPERTY_DESCRIPTOR",
"value":"999-999-9999"}
,{"name":"LOCATION_PROPERTY_DESCRIPTOR",
"value":"New York, NY"}
],
			"title": "LA2TVXkOeT",
			"managerId": "6DXHo",
			"teamId": "NO_TEAM_ID",
			"isManager": "false"
		},
		{
			"serializationDescriptor": {
				"name": "IndividualContributor",
				"objectVersion": "1"
			},
			"id": "T6SvM",
			"name": "JWlFbx 7HoAMv",
			"properties": [{"name":"PHONE_PROPERTY_DESCRIPTOR",
"value":"999-999-9999"}
,{"name":"LOCATION_PROPERTY_DESCRIPTOR",
"value":"San Francisco, CA"}
],
			"title": "bBDzJU2Txu",
			"managerId": "6DXHo",
			"teamId": "NO_TEAM_ID",
			"isManager": "false"
		},
		{
			"serializationDescriptor": {
				"name": "Manager",
				"objectVersion": "1"
			},
			"id": "vOoOK",
			"name": "4jMBfj Ev7EOY",
			"properties": [{"name":"PHONE_PROPERTY_DESCRIPTOR",
"value":"999-999-9999"}
,{"name":"LOCATION_PROPERTY_DESCRIPTOR",
"value":"New York, NY"}
],
			"title": "diBr9N9qtn",
			"managerId": "6DXHo",
			"teamId": "NO_TEAM_ID",
			"isManager": "true"
		},
		{
			"serializationDescriptor": {
				"name": "Manager",
				"objectVersion": "1"
			},
			"id": "qHpgN",
			"name": "z1fZXm jsJfYA",
			"properties": [{"name":"PHONE_PROPERTY_DESCRIPTOR",
"value":"999-999-9999"}
,{"name":"LOCATION_PROPERTY_DESCRIPTOR",
"value":"New York, NY"}
],
			"title": "cw0Fv3q4n3",
			"managerId": "6DXHo",
			"teamId": "NO_TEAM_ID",
			"isManager": "true"
		},
		{
			"serializationDescriptor": {
				"name": "Manager",
				"objectVersion": "1"
			},
			"id": "UE9DA",
			"name": "EMiSxW pE5P9o",
			"properties": [{"name":"PHONE_PROPERTY_DESCRIPTOR",
"value":"999-999-9999"}
,{"name":"LOCATION_PROPERTY_DESCRIPTOR",
"value":"New York, NY"}
],
			"title": "Q4PRnBDH0A",
			"managerId": "6DXHo",
			"teamId": "NO_TEAM_ID",
			"isManager": "true"
		},
		{
			"serializationDescriptor": {
				"name": "IndividualContributor",
				"objectVersion": "1"
			},
			"id": "8UTsR",
			"name": "W3MHfV WY4XzD",
			"properties": [{"name":"PHONE_PROPERTY_DESCRIPTOR",
"value":"999-999-9999"}
,{"name":"LOCATION_PROPERTY_DESCRIPTOR",
"value":"New York, NY"}
],
			"title": "u9cvZPO1kO",
			"managerId": "127AO",
			"teamId": "NO_TEAM_ID",
			"isManager": "false"
		},
		{
			"serializationDescriptor": {
				"name": "IndividualContributor",
				"objectVersion": "1"
			},
			"id": "s47eh",
			"name": "mHIcsN e4MP0M",
			"properties": [{"name":"PHONE_PROPERTY_DESCRIPTOR",
"value":"999-999-9999"}
,{"name":"LOCATION_PROPERTY_DESCRIPTOR",
"value":"San Francisco, CA"}
],
			"title": "Up96tQzuqh",
			"managerId": "127AO",
			"teamId": "NO_TEAM_ID",
			"isManager": "false"
		},
		{
			"serializationDescriptor": {
				"name": "IndividualContributor",
				"objectVersion": "1"
			},
			"id": "OVQqZ",
			"name": "ZEvxnq NMqeXW",
			"properties": [{"name":"PHONE_PROPERTY_DESCRIPTOR",
"value":"999-999-9999"}
,{"name":"LOCATION_PROPERTY_DESCRIPTOR",
"value":"Austin, TX"}
],
			"title": "9CL5CODzcd",
			"managerId": "127AO",
			"teamId": "NO_TEAM_ID",
			"isManager": "false"
		},
		{
			"serializationDescriptor": {
				"name": "Manager",
				"objectVersion": "1"
			},
			"id": "jNKwe",
			"name": "2bk5Vx 0xnu1j",
			"properties": [{"name":"PHONE_PROPERTY_DESCRIPTOR",
"value":"999-999-9999"}
,{"name":"LOCATION_PROPERTY_DESCRIPTOR",
"value":"San Francisco, CA"}
],
			"title": "BfO69UGFqN",
			"managerId": "127AO",
			"teamId": "NO_TEAM_ID",
			"isManager": "true"
		},
		{
			"serializationDescriptor": {
				"name": "Manager",
				"objectVersion": "1"
			},
			"id": "77hfO",
			"name": "G0L37V tnYm1t",
			"properties": [{"name":"PHONE_PROPERTY_DESCRIPTOR",
"value":"999-999-9999"}
,{"name":"LOCATION_PROPERTY_DESCRIPTOR",
"value":"New York, NY"}
],
			"title": "yhtFKiGnOw",
			"managerId": "127AO",
			"teamId": "NO_TEAM_ID",
			"isManager": "true"
		},
		{
			"serializationDescriptor": {
				"name": "Manager",
				"objectVersion": "1"
			},
			"id": "CG7K0",
			"name": "tqvoN7 QWAeBa",
			"properties": [{"name":"PHONE_PROPERTY_DESCRIPTOR",
"value":"999-999-9999"}
,{"name":"LOCATION_PROPERTY_DESCRIPTOR",
"value":"San Francisco, CA"}
],
			"title": "nGkti2L4wv",
			"managerId": "127AO",
			"teamId": "NO_TEAM_ID",
			"isManager": "true"
		},
		{
			"serializationDescriptor": {
				"name": "IndividualContributor",
				"objectVersion": "1"
			},
			"id": "2pneO",
			"name": "CL0PzT 24LNNI",
			"properties": [{"name":"PHONE_PROPERTY_DESCRIPTOR",
"value":"999-999-9999"}
,{"name":"LOCATION_PROPERTY_DESCRIPTOR",
"value":"New York, NY"}
],
			"title": "oGX4uh1olL",
			"managerId": "J6aJB",
			"teamId": "NO_TEAM_ID",
			"isManager": "false"
		},
		{
			"serializationDescriptor": {
				"name": "IndividualContributor",
				"objectVersion": "1"
			},
			"id": "OTjVk",
			"name": "Yw3okp dofOzT",
			"properties": [{"name":"PHONE_PROPERTY_DESCRIPTOR",
"value":"999-999-9999"}
,{"name":"LOCATION_PROPERTY_DESCRIPTOR",
"value":"Austin, TX"}
],
			"title": "MAIvY2OVrl",
			"managerId": "J6aJB",
			"teamId": "NO_TEAM_ID",
			"isManager": "false"
		},
		{
			"serializationDescriptor": {
				"name": "Manager",
				"objectVersion": "1"
			},
			"id": "ebD3t",
			"name": "mv1QRM H8Oxos",
			"properties": [{"name":"PHONE_PROPERTY_DESCRIPTOR",
"value":"999-999-9999"}
,{"name":"LOCATION_PROPERTY_DESCRIPTOR",
"value":"New York, NY"}
],
			"title": "EpKBN6WvyL",
			"managerId": "J6aJB",
			"teamId": "NO_TEAM_ID",
			"isManager": "true"
		},
		{
			"serializationDescriptor": {
				"name": "IndividualContributor",
				"objectVersion": "1"
			},
			"id": "5pbCx",
			"name": "lrFqA9 VZg86J",
			"properties": [{"name":"PHONE_PROPERTY_DESCRIPTOR",
"value":"999-999-9999"}
,{"name":"LOCATION_PROPERTY_DESCRIPTOR",
"value":"Austin, TX"}
],
			"title": "0fp9DGZMNr",
			"managerId": "IXhya",
			"teamId": "NO_TEAM_ID",
			"isManager": "false"
		},
		{
			"serializationDescriptor": {
				"name": "IndividualContributor",
				"objectVersion": "1"
			},
			"id": "9sBhZ",
			"name": "ZQ1kw4 CTeyRE",
			"properties": [{"name":"PHONE_PROPERTY_DESCRIPTOR",
"value":"999-999-9999"}
,{"name":"LOCATION_PROPERTY_DESCRIPTOR",
"value":"Austin, TX"}
],
			"title": "hcAjxFeDI2",
			"managerId": "QZkJj",
			"teamId": "NO_TEAM_ID",
			"isManager": "false"
		},
		{
			"serializationDescriptor": {
				"name": "IndividualContributor",
				"objectVersion": "1"
			},
			"id": "736s8",
			"name": "eRatjw n8hBSi",
			"properties": [{"name":"PHONE_PROPERTY_DESCRIPTOR",
"value":"999-999-9999"}
,{"name":"LOCATION_PROPERTY_DESCRIPTOR",
"value":"Austin, TX"}
],
			"title": "HjQfSR3e5q",
			"managerId": "vOoOK",
			"teamId": "NO_TEAM_ID",
			"isManager": "false"
		},
		{
			"serializationDescriptor": {
				"name": "IndividualContributor",
				"objectVersion": "1"
			},
			"id": "Ed4zV",
			"name": "RPL3QK fLWbV6",
			"properties": [{"name":"PHONE_PROPERTY_DESCRIPTOR",
"value":"999-999-9999"}
,{"name":"LOCATION_PROPERTY_DESCRIPTOR",
"value":"Austin, TX"}
],
			"title": "ptXuAQBirQ",
			"managerId": "qHpgN",
			"teamId": "NO_TEAM_ID",
			"isManager": "false"
		},
		{
			"serializationDescriptor": {
				"name": "IndividualContributor",
				"objectVersion": "1"
			},
			"id": "8ZmIF",
			"name": "1CdTA0 WLUAH3",
			"properties": [{"name":"PHONE_PROPERTY_DESCRIPTOR",
"value":"999-999-9999"}
,{"name":"LOCATION_PROPERTY_DESCRIPTOR",
"value":"San Francisco, CA"}
],
			"title": "5kM3LthU9U",
			"managerId": "UE9DA",
			"teamId": "NO_TEAM_ID",
			"isManager": "false"
		},
		{
			"serializationDescriptor": {
				"name": "IndividualContributor",
				"objectVersion": "1"
			},
			"id": "rcCuM",
			"name": "e3FSWK Ow7r6Q",
			"properties": [{"name":"PHONE_PROPERTY_DESCRIPTOR",
"value":"999-999-9999"}
,{"name":"LOCATION_PROPERTY_DESCRIPTOR",
"value":"San Francisco, CA"}
],
			"title": "3wjPWV0elq",
			"managerId": "jNKwe",
			"teamId": "NO_TEAM_ID",
			"isManager": "false"
		},
		{
			"serializationDescriptor": {
				"name": "IndividualContributor",
				"objectVersion": "1"
			},
			"id": "WxjAB",
			"name": "svFQWA QcOMss",
			"properties": [{"name":"PHONE_PROPERTY_DESCRIPTOR",
"value":"999-999-9999"}
,{"name":"LOCATION_PROPERTY_DESCRIPTOR",
"value":"San Francisco, CA"}
],
			"title": "TsYZw2696S",
			"managerId": "77hfO",
			"teamId": "NO_TEAM_ID",
			"isManager": "false"
		},
		{
			"serializationDescriptor": {
				"name": "IndividualContributor",
				"objectVersion": "1"
			},
			"id": "4vnCZ",
			"name": "wExv4B 6vcTJR",
			"properties": [{"name":"PHONE_PROPERTY_DESCRIPTOR",
"value":"999-999-9999"}
,{"name":"LOCATION_PROPERTY_DESCRIPTOR",
"value":"Austin, TX"}
],
			"title": "MWu9xfBtJR",
			"managerId": "CG7K0",
			"teamId": "NO_TEAM_ID",
			"isManager": "false"
		}],
		"teams": [{
			"serializationDescriptor": {
				"name": "Team",
				"objectVersion": "1"
			},
			"id": "NO_TEAM_ID",
			"title": "-- No Team --",
			"managerId": "ROOT_ID"
		},
		{
			"serializationDescriptor": {
				"name": "Team",
				"objectVersion": "1"
			},
			"id": "b566f7a3-19d7-4608-9e96-327bcbb1b2b0",
			"title": "Your Organization",
			"managerId": "ROOT_ID"
		}]
	}
}