{
	"serializationDescriptor": {
		"name": "OrgDataCore",
		"objectVersion": "1"
	},
	"title": "E",
	"orgStructure": {
		"serializationDescriptor": {
			"name": "OrgStructure",
			"objectVersion": "1"
		},
		"employeePropertyDescriptors": [{
			"serializationDescriptor": {
				"name": "OrgEntityPropertyDescriptor",
				"objectVersion": "1"
			},
			"name": "PHONE_PROPERTY_DESCRIPTOR",
			"title": "Phone",
			"defaultValue": "999-999-9999",
			"enabled": "true"
		},
		{
			"serializationDescriptor": {
				"name": "OrgEntityPropertyDescriptor",
				"objectVersion": "1"
			},
			"name": "LOCATION_PROPERTY_DESCRIPTOR",
			"title": "Location",
			"defaultValue": "San Francisco",
			"enabled": "true"
		}],
		"employees": [{
			"serializationDescriptor": {
				"name": "Manager",
				"objectVersion": "1"
			},
			"id": "75e6f213-7b77-47e5-a4db-fb658421cec2",
			"name": "First Last",
			"properties": [{"name":"PHONE_PROPERTY_DESCRIPTOR",
"value":"999-999-9999"}
,{"name":"LOCATION_PROPERTY_DESCRIPTOR",
"value":"San Francisco"}
],
			"title": "Senior Vice President",
			"managerId": "ROOT_ID",
			"teamId": "aaf6c046-9f84-4fea-8f50-50e2e5b4b34e",
			"isManager": "true"
		},
		{
			"serializationDescriptor": {
				"name": "IndividualContributor",
				"objectVersion": "1"
			},
			"id": "DEFiW",
			"name": "3hNOC8 obBmbe",
			"properties": [{"name":"PHONE_PROPERTY_DESCRIPTOR",
"value":"999-999-9999"}
,{"name":"LOCATION_PROPERTY_DESCRIPTOR",
"value":"New York, NY"}
],
			"title": "0Xt1NoY2mz",
			"managerId": "75e6f213-7b77-47e5-a4db-fb658421cec2",
			"teamId": "NO_TEAM_ID",
			"isManager": "false"
		},
		{
			"serializationDescriptor": {
				"name": "IndividualContributor",
				"objectVersion": "1"
			},
			"id": "7O2rp",
			"name": "3KvLzC POR8pq",
			"properties": [{"name":"PHONE_PROPERTY_DESCRIPTOR",
"value":"999-999-9999"}
,{"name":"LOCATION_PROPERTY_DESCRIPTOR",
"value":"Austin, TX"}
],
			"title": "RurTOOOQ1N",
			"managerId": "75e6f213-7b77-47e5-a4db-fb658421cec2",
			"teamId": "NO_TEAM_ID",
			"isManager": "false"
		},
		{
			"serializationDescriptor": {
				"name": "IndividualContributor",
				"objectVersion": "1"
			},
			"id": "Z3d4u",
			"name": "j38UZm U0dMcJ",
			"properties": [{"name":"PHONE_PROPERTY_DESCRIPTOR",
"value":"999-999-9999"}
,{"name":"LOCATION_PROPERTY_DESCRIPTOR",
"value":"New York, NY"}
],
			"title": "o3e1HsuaFm",
			"managerId": "75e6f213-7b77-47e5-a4db-fb658421cec2",
			"teamId": "NO_TEAM_ID",
			"isManager": "false"
		},
		{
			"serializationDescriptor": {
				"name": "IndividualContributor",
				"objectVersion": "1"
			},
			"id": "d9DNd",
			"name": "9fuhWn HYkid4",
			"properties": [{"name":"PHONE_PROPERTY_DESCRIPTOR",
"value":"999-999-9999"}
,{"name":"LOCATION_PROPERTY_DESCRIPTOR",
"value":"San Francisco, CA"}
],
			"title": "sNThSXbSpN",
			"managerId": "75e6f213-7b77-47e5-a4db-fb658421cec2",
			"teamId": "NO_TEAM_ID",
			"isManager": "false"
		},
		{
			"serializationDescriptor": {
				"name": "IndividualContributor",
				"objectVersion": "1"
			},
			"id": "RVZYC",
			"name": "xKXWph HFkstF",
			"properties": [{"name":"PHONE_PROPERTY_DESCRIPTOR",
"value":"999-999-9999"}
,{"name":"LOCATION_PROPERTY_DESCRIPTOR",
"value":"San Francisco, CA"}
],
			"title": "1GIJr9DGgE",
			"managerId": "75e6f213-7b77-47e5-a4db-fb658421cec2",
			"teamId": "NO_TEAM_ID",
			"isManager": "false"
		},
		{
			"serializationDescriptor": {
				"name": "IndividualContributor",
				"objectVersion": "1"
			},
			"id": "kIqGE",
			"name": "lE0UZi njFtzg",
			"properties": [{"name":"PHONE_PROPERTY_DESCRIPTOR",
"value":"999-999-9999"}
,{"name":"LOCATION_PROPERTY_DESCRIPTOR",
"value":"Austin, TX"}
],
			"title": "CnB4ns8VUL",
			"managerId": "75e6f213-7b77-47e5-a4db-fb658421cec2",
			"teamId": "NO_TEAM_ID",
			"isManager": "false"
		},
		{
			"serializationDescriptor": {
				"name": "IndividualContributor",
				"objectVersion": "1"
			},
			"id": "dPvGj",
			"name": "nOeRGM CRx5Ln",
			"properties": [{"name":"PHONE_PROPERTY_DESCRIPTOR",
"value":"999-999-9999"}
,{"name":"LOCATION_PROPERTY_DESCRIPTOR",
"value":"Austin, TX"}
],
			"title": "RTzMYNEwUg",
			"managerId": "75e6f213-7b77-47e5-a4db-fb658421cec2",
			"teamId": "NO_TEAM_ID",
			"isManager": "false"
		},
		{
			"serializationDescriptor": {
				"name": "IndividualContributor",
				"objectVersion": "1"
			},
			"id": "0Y7dJ",
			"name": "jvOCf6 cJan41",
			"properties": [{"name":"PHONE_PROPERTY_DESCRIPTOR",
"value":"999-999-9999"}
,{"name":"LOCATION_PROPERTY_DESCRIPTOR",
"value":"New York, NY"}
],
			"title": "HqNxCVgPNR",
			"managerId": "75e6f213-7b77-47e5-a4db-fb658421cec2",
			"teamId": "NO_TEAM_ID",
			"isManager": "false"
		},
		{
			"serializationDescriptor": {
				"name": "IndividualContributor",
				"objectVersion": "1"
			},
			"id": "wUaxT",
			"name": "CKpqx0 oMWp4X",
			"properties": [{"name":"PHONE_PROPERTY_DESCRIPTOR",
"value":"999-999-9999"}
,{"name":"LOCATION_PROPERTY_DESCRIPTOR",
"value":"New York, NY"}
],
			"title": "g10MdCXOAL",
			"managerId": "75e6f213-7b77-47e5-a4db-fb658421cec2",
			"teamId": "NO_TEAM_ID",
			"isManager": "false"
		},
		{
			"serializationDescriptor": {
				"name": "IndividualContributor",
				"objectVersion": "1"
			},
			"id": "vDUP0",
			"name": "XO0UIK yvNLOO",
			"properties": [{"name":"PHONE_PROPERTY_DESCRIPTOR",
"value":"999-999-9999"}
,{"name":"LOCATION_PROPERTY_DESCRIPTOR",
"value":"San Francisco, CA"}
],
			"title": "eeQy6FLGp5",
			"managerId": "75e6f213-7b77-47e5-a4db-fb658421cec2",
			"teamId": "NO_TEAM_ID",
			"isManager": "false"
		},
		{
			"serializationDescriptor": {
				"name": "Manager",
				"objectVersion": "1"
			},
			"id": "UDTQ9",
			"name": "GAFGe2 OxX456",
			"properties": [{"name":"PHONE_PROPERTY_DESCRIPTOR",
"value":"999-999-9999"}
,{"name":"LOCATION_PROPERTY_DESCRIPTOR",
"value":"New York, NY"}
],
			"title": "8GQCxcBLVH",
			"managerId": "75e6f213-7b77-47e5-a4db-fb658421cec2",
			"teamId": "NO_TEAM_ID",
			"isManager": "true"
		},
		{
			"serializationDescriptor": {
				"name": "Manager",
				"objectVersion": "1"
			},
			"id": "1DVJm",
			"name": "nBZAU1 P9UQkN",
			"properties": [{"name":"PHONE_PROPERTY_DESCRIPTOR",
"value":"999-999-9999"}
,{"name":"LOCATION_PROPERTY_DESCRIPTOR",
"value":"New York, NY"}
],
			"title": "ZkpdutyyzC",
			"managerId": "75e6f213-7b77-47e5-a4db-fb658421cec2",
			"teamId": "NO_TEAM_ID",
			"isManager": "true"
		},
		{
			"serializationDescriptor": {
				"name": "Manager",
				"objectVersion": "1"
			},
			"id": "0CnuG",
			"name": "M0MRTx IoemXg",
			"properties": [{"name":"PHONE_PROPERTY_DESCRIPTOR",
"value":"999-999-9999"}
,{"name":"LOCATION_PROPERTY_DESCRIPTOR",
"value":"Austin, TX"}
],
			"title": "UfI1ADnyGQ",
			"managerId": "75e6f213-7b77-47e5-a4db-fb658421cec2",
			"teamId": "NO_TEAM_ID",
			"isManager": "true"
		},
		{
			"serializationDescriptor": {
				"name": "IndividualContributor",
				"objectVersion": "1"
			},
			"id": "mWAjW",
			"name": "yH1IMW i5xIUj",
			"properties": [{"name":"PHONE_PROPERTY_DESCRIPTOR",
"value":"999-999-9999"}
,{"name":"LOCATION_PROPERTY_DESCRIPTOR",
"value":"New York, NY"}
],
			"title": "ElqS80kQfV",
			"managerId": "UDTQ9",
			"teamId": "NO_TEAM_ID",
			"isManager": "false"
		},
		{
			"serializationDescriptor": {
				"name": "IndividualContributor",
				"objectVersion": "1"
			},
			"id": "oJfyC",
			"name": "UIG8Z6 I5CAXR",
			"properties": [{"name":"PHONE_PROPERTY_DESCRIPTOR",
"value":"999-999-9999"}
,{"name":"LOCATION_PROPERTY_DESCRIPTOR",
"value":"New York, NY"}
],
			"title": "llDKiZ7psX",
			"managerId": "UDTQ9",
			"teamId": "NO_TEAM_ID",
			"isManager": "false"
		},
		{
			"serializationDescriptor": {
				"name": "IndividualContributor",
				"objectVersion": "1"
			},
			"id": "dfpgX",
			"name": "evtzT5 euxuAa",
			"properties": [{"name":"PHONE_PROPERTY_DESCRIPTOR",
"value":"999-999-9999"}
,{"name":"LOCATION_PROPERTY_DESCRIPTOR",
"value":"San Francisco, CA"}
],
			"title": "7HrXQ0RUYz",
			"managerId": "UDTQ9",
			"teamId": "NO_TEAM_ID",
			"isManager": "false"
		},
		{
			"serializationDescriptor": {
				"name": "IndividualContributor",
				"objectVersion": "1"
			},
			"id": "S6qWf",
			"name": "3RlaQo 317N6N",
			"properties": [{"name":"PHONE_PROPERTY_DESCRIPTOR",
"value":"999-999-9999"}
,{"name":"LOCATION_PROPERTY_DESCRIPTOR",
"value":"Austin, TX"}
],
			"title": "V26s1AXLUw",
			"managerId": "UDTQ9",
			"teamId": "NO_TEAM_ID",
			"isManager": "false"
		},
		{
			"serializationDescriptor": {
				"name": "Manager",
				"objectVersion": "1"
			},
			"id": "hd6zY",
			"name": "ksza7e iErmZQ",
			"properties": [{"name":"PHONE_PROPERTY_DESCRIPTOR",
"value":"999-999-9999"}
,{"name":"LOCATION_PROPERTY_DESCRIPTOR",
"value":"Austin, TX"}
],
			"title": "jqMR1T17Aa",
			"managerId": "UDTQ9",
			"teamId": "NO_TEAM_ID",
			"isManager": "true"
		},
		{
			"serializationDescriptor": {
				"name": "IndividualContributor",
				"objectVersion": "1"
			},
			"id": "wXVSr",
			"name": "ogwwdO NrKrcj",
			"properties": [{"name":"PHONE_PROPERTY_DESCRIPTOR",
"value":"999-999-9999"}
,{"name":"LOCATION_PROPERTY_DESCRIPTOR",
"value":"Austin, TX"}
],
			"title": "lMNemLF0lp",
			"managerId": "1DVJm",
			"teamId": "NO_TEAM_ID",
			"isManager": "false"
		},
		{
			"serializationDescriptor": {
				"name": "IndividualContributor",
				"objectVersion": "1"
			},
			"id": "Gk1lF",
			"name": "v7eZkt YwrAzD",
			"properties": [{"name":"PHONE_PROPERTY_DESCRIPTOR",
"value":"999-999-9999"}
,{"name":"LOCATION_PROPERTY_DESCRIPTOR",
"value":"New York, NY"}
],
			"title": "Bpn5gqFl9I",
			"managerId": "1DVJm",
			"teamId": "NO_TEAM_ID",
			"isManager": "false"
		},
		{
			"serializationDescriptor": {
				"name": "IndividualContributor",
				"objectVersion": "1"
			},
			"id": "wQnXd",
			"name": "9yrpat C6rdh4",
			"properties": [{"name":"PHONE_PROPERTY_DESCRIPTOR",
"value":"999-999-9999"}
,{"name":"LOCATION_PROPERTY_DESCRIPTOR",
"value":"Austin, TX"}
],
			"title": "bzdbgLAHrk",
			"managerId": "1DVJm",
			"teamId": "NO_TEAM_ID",
			"isManager": "false"
		},
		{
			"serializationDescriptor": {
				"name": "IndividualContributor",
				"objectVersion": "1"
			},
			"id": "CnQJm",
			"name": "koYO9N PK4joX",
			"properties": [{"name":"PHONE_PROPERTY_DESCRIPTOR",
"value":"999-999-9999"}
,{"name":"LOCATION_PROPERTY_DESCRIPTOR",
"value":"Austin, TX"}
],
			"title": "A0uJgaCXVv",
			"managerId": "0CnuG",
			"teamId": "NO_TEAM_ID",
			"isManager": "false"
		},
		{
			"serializationDescriptor": {
				"name": "IndividualContributor",
				"objectVersion": "1"
			},
			"id": "9CKTA",
			"name": "Jq9Isf zAGkIw",
			"properties": [{"name":"PHONE_PROPERTY_DESCRIPTOR",
"value":"999-999-9999"}
,{"name":"LOCATION_PROPERTY_DESCRIPTOR",
"value":"New York, NY"}
],
			"title": "hblOjlpFYD",
			"managerId": "0CnuG",
			"teamId": "NO_TEAM_ID",
			"isManager": "false"
		},
		{
			"serializationDescriptor": {
				"name": "IndividualContributor",
				"objectVersion": "1"
			},
			"id": "1AX3N",
			"name": "4vH5Pe LtWTsW",
			"properties": [{"name":"PHONE_PROPERTY_DESCRIPTOR",
"value":"999-999-9999"}
,{"name":"LOCATION_PROPERTY_DESCRIPTOR",
"value":"Austin, TX"}
],
			"title": "drxnu2hNPl",
			"managerId": "0CnuG",
			"teamId": "NO_TEAM_ID",
			"isManager": "false"
		}],
		"teams": [{
			"serializationDescriptor": {
				"name": "Team",
				"objectVersion": "1"
			},
			"id": "NO_TEAM_ID",
			"title": "-- No Team --",
			"managerId": "ROOT_ID"
		},
		{
			"serializationDescriptor": {
				"name": "Team",
				"objectVersion": "1"
			},
			"id": "aaf6c046-9f84-4fea-8f50-50e2e5b4b34e",
			"title": "FIX ME",
			"managerId": "ROOT_ID"
		}]
	}
}